Workbook

Sheet 2026
B2: MONTH | C2: INCOME | G2: SPENDING | N2: TOTAL SPENT | O2: REST | P2: TOTAL DEPOSIT | R2: Total Savings
C3: TOTAL | D3: LOAN | E3: SALARY | F3: BONUS | G3: SPENDING | H3: TAX | I3: DPS | J3: CITY LOAN | K3: SCB LOAN | L3: EBL LOAN | M3: LENT
B4: MAR | C4: =SUM(D4:F4) -> 146431 | D4: 50000 | E4: 68400 | F4: =ROUND(((60000*8+32727+68400*2+68400*(20/31))/(60000*9+68400*2+68400*(20/31))*(354/365))*(30000*9/12+34200*2.645/12),0) -> 28031 | G4: =-20000+104-501 -> -20397 | H4: =-(5000-666*2)/5+1 -> -732.6 | I4: -15000 | J4: -15301 | K4: 0 | L4: 0 | M4: -95000 | N4: =SUM(G4:H4,J4:M4) -> -131430.6 | O4: =SUM(D4:M4) -> 0.4 | P4: 0 | R4: =P14 -> 0
B5: APR | C5: =SUM(D5:F5) -> 68400 | D5: 0 | E5: 68400 | F5: 0 | G5: =-20000+4296-500+575 -> -15629 | H5: =-(5000-666*2)/5 -> -733.6 | I5: -15000 | J5: -15301 | K5: -12334 | L5: =-8827-575 -> -9402 | M5: 0 | N5: =SUM(G5:H5,J5:M5) -> -53399.6 | O5: =SUM(E5:M5) -> 0.4 | P5: 0 | R5: 0
B6: MAY | C6: =SUM(D6:F6) -> 98400 | D6: 0 | E6: 68400 | F6: =30000 -> 30000 | G6: =-20000+4296-500 -> -16204 | H6: =-(5000-666*2)/5 -> -733.6 | I6: 0 | J6: -15301 | K6: -12334 | L6: =-8975-35000 -> -43975 | M6: 0 | N6: =SUM(G6:H6,J6:M6) -> -88547.6 | O6: 0 | P6: =-I6 -> 0 | R6: 303200
B7: JUN | C7: =SUM(D7:F7) -> 68400 | D7: 0 | E7: 68400 | F7: 0 | G7: =-20000+1374-500 -> -19126 | H7: =-(5000-666*2)/5 -> -733.6 | I7: -15000 | J7: 0 | K7: -12334 | L7: 0 | M7: 0 | N7: =SUM(G7:H7,J7:M7) -> -32193.6 | O7: 0 | P7: 0 | R7: =SUM(R4:R6) -> 303200
B8: JUL | C8: =SUM(D8:F8) -> 68400 | D8: 0 | E8: 68400 | F8: 0 | G8: =-20000 -> -20000 | H8: =-(5000-666*2)/5 -> -733.6 | I8: -5000 | J8: 0 | K8: -12334 | L8: 0 | M8: 0 | N8: =SUM(G8:H8,J8:M8) -> -33067.6 | O8: 0 | P8: 0 | R8: 0
B9: AUG | C9: =SUM(D9:F9) -> 68400 | D9: 0 | E9: 68400 | F9: 0 | G9: =-20000 -> -20000 | H9: -416 | I9: 0 | J9: 0 | K9: =-12333.33 -> -12333.33 | L9: 0 | M9: 0 | N9: =SUM(G9:H9,J9:M9) -> -32749.33 | O9: 0 | P9: 0 | R9: =SUM(R7,R8) -> 303200
B10: SEP | C10: =SUM(D10:F10) -> 68400 | D10: 0 | E10: 68400 | F10: 0 | G10: =-20000 -> -20000 | H10: -416 | I10: 0 | J10: 0 | K10: =-EMIs!I6 -> -41149.57 | L10: 0 | M10: 0 | N10: =SUM(G10:H10,J10:M10) -> -61565.57 | O10: 0 | P10: 0
B11: OCT | C11: =SUM(D11:F11) -> 68400 | D11: 0 | E11: 68400 | F11: 0 | G11: -20000 | H11: -416 | I11: 0 | J11: 0 | K11: =-SUM(EMIs!I4,EMIs!I5) -> -28816.24 | L11: 0 | M11: 0 | N11: =SUM(G11:H11,J11:M11) -> -49232.24 | O11: 0 | P11: 0
B12: NOV | C12: =SUM(D12:F12) -> 68400 | D12: 0 | E12: 68400 | F12: 0 | G12: -20000 | H12: -416 | I12: 0 | J12: 0 | K12: =-SUM(EMIs!I4,EMIs!I5) -> -28816.24 | L12: 0 | M12: 0 | N12: =SUM(G12:M12) -> -49232.24 | O12: =sum(D12:M12) -> 19167.76 | P12: 0
B13: DEC | C13: =SUM(D13:F13) -> 68400 | D13: 0 | E13: 68400 | F13: 0 | G13: -20000 | H13: -416 | I13: 0 | J13: 0 | K13: 0 | L13: 0 | M13: 0 | N13: =SUM(G13:H13,J13:M13) -> -20416 | O13: 0 | P13: 0
B14: Yearly Total | C14: =SUM(C4:C13) -> 792031 | D14: =SUM(D4:D13) -> 50000 | E14: =SUM(E4:E13) -> 684000 | F14: =SUM(F4:F13) -> 58031 | G14: =SUM(G4:G13) -> -191356 | H14: =SUM(H4:H13) -> -5747 | I14: =SUM(I4:I13) -> -50000 | J14: =SUM(J4:J13) -> -45903 | ... N14: =SUM(N4:N13) -> -551834.38 | O14: 0 | P14: =SUM(P4:P13) -> 0

Sheet Current Month Breakdown
B2: INFLOW | E2: OUTFLOW | H2: REMAINING
B3: ITEM | C3: AMOUNT | E3: ITEM | F3: AMOUNT | H3: =C7-F9 -> -11897.3 | I3: 46309
B4: PRIME NOW | C4: 4934.26 | E4: CREDIT CARDS | F4: =C16 -> 17691.56
B5: MBD PREPAID | C5: 0 | F5: 0
B6: CASH | C6: 860 | F6: 0
B7: CREDIT | C7: =SUM(C4:C6) -> 5794.26 | F7: 0
F8: 0
E9: DEBIT | F9: =SUM(F4:F8) -> 17691.56
B11: CREDIT CARD BILLS | E11: REMAINING CREDIT CARD BILLS
B12: CARD | C12: AMOUNT | E12: SCB TOTAL DEBT ON SEP 10, 2026
B13: SCB | C13: 481.52 | E13: NBL TOTAL DEBT ON SEP 10, 2026
B14: EBL | C14: 1248.2 | E14: TOTAL DEBT | F14: =SUM(F12:F13) -> 0
B15: NBL | C15: 15961.84
B16: TOTAL | C16: =SUM(C13:C15) -> 17691.56

Sheet October 2026 GPU Planning
B2: INFLOW | E2: OUTFLOW | H2: REMAINING
B3: ITEM | C3: AMOUNT | E3: ITEM | F3: AMOUNT | H3: =C7-F10 -> 5644.26
B4: PRIME NOW | C4: =69264.26 -> 69264.26 | E4: NBL | F4: =40000 -> 40000
B5: MBD PREPAID | C5: 0 | E5: SCB | F5: =148300-113680+round('2026'!K12,0)-2653 -> 3151
B6: CASH | C6: 0 | E6: EBL | F6: 6002 | H6: CREDIT CARD DEBT
B7: CREDIT | C7: =SUM(C4:C6) -> 69264.26 | E7: NASCENIA SAVINGS 101 | F7: 5000 | H7: CARD | I7: AMOUNT
E8: RENT | F8: 6967 | H8: NBL ON OCT 08, 2026 | I8: 17000
E9: OFFICE FOOD | F9: 2500 | H9: TOTAL | I9: =SUM(I8) -> 17000
E10: DEBIT | F10: =SUM(F4:F9) -> 63620

Sheet EMIs
B2: No | C2: Bank | D2: Disbursed Date | E2: Start Date | F2: End Date | G2: Principal Amount | H2: Expenses | I2: EMI Amount | J2: Duration (in months) | K2: Total EMI Payment | L2: Total Paid | M2: Repaid | O2: Total Loam Amount
B3: 1 | C3: SCB Credit | D3: 46047 | E3: 46122 | F3: 46274 | G3: 74000 | H3: 3404 | I3: =round(G3/J3, 2) -> 12333.33 | J3: 6 | K3: =I3*J3 -> 73999.98 | L3: =SUM(G3,H3) -> 77404 | M3: No | O3: =L6 -> 163852.72
B4: 2 | C4: SCB Credit | D4: 46215 | E4: 46243 | F4: 46335 | G4: 63300 | H4: 0 | I4: =round(G4/J4, 2) -> 21100 | J4: 3 | K4: =I4*J4 -> 63300 | L4: =G4+H4 -> 63300 | M4: No
B5: 3 | C5: SCB Credit | D5: 46218 | E5: 46243 | F5: 46335 | G5: 23148.72 | H5: 0 | I5: =round(G5/J5, 2) -> 7716.24 | J5: 3 | K5: =I5*J5 -> 23148.72 | L5: =SUM(G5,H5) -> 23148.72 | M5: No
B6: Total | E6: =MIN(E3:E5) -> 46122 | F6: =MAX(F3:F5) -> 46335 | G6: =SUM(G3:G5) -> 160448.72 | H6: =SUM(H3:H5) -> 3404 | I6: =SUM(I3:I5) -> 41149.57 | J6: =MAX(J3:J5) -> 6 | K6: =SUM(K3:K5) -> 160448.7 | L6: =SUM(L3:L5) -> 163852.72 | M6: No

Sheet INVESTMENT
B2: No | C2: Investment Date | D2: Investment Time | E2: Investment Day | F2: Return Date | G2: Organization | H2: Method | I2: Transaction Proof Document 1 | J2: Order Details | K2: Transaction Proof Document 1 | L2: Investment Amount | M2: Return Amount | N2: Profit | P2: Total Investment
B3: 1 | C3: 45979 | D3: 0.93819444 | E3: Tuesday | F3: 46406 | G3: iFarmer | H3: EBL to EBL | I3: SkyBanking_iFarmer_Payment_Receipt.jpeg | J3: ifarmer_order_details.jpg | K3: Gmail_iFarmer_Transaction_Alert.pdf | L3: 130000 | M3: 160550 | N3: =M3-L3 -> 30550 | P3: =L6 -> 252000
B4: 2 | C4: 46048 | D4: 0.77430556 | E4: Monday | F4: 46473 | G4: iFarmer | H4: EBL to EBL | I4: 8. SkyBanking_iFarmer_Payment_Receipt_103147.png | L4: 12000 | M4: 14520 | N4: =M4-L4 -> 2520
B5: 3 | C5: 46049 | D5: 0.48125 | E5: Tuesday | F5: 46353 | G5: iFarmer | H5: EBL to EBL | I5: 9. SkyBanking_iFarmer_Payment_Receipt_103202.png | L5: 110000 | M5: 128150 | N5: =M5-L5 -> 18150
B6: Total | L6: =SUM(L3:L5) -> 252000 | M6: =SUM(M3:M5) -> 303220 | N6: =SUM(N3:N5) -> 51220

Sheet LOANS
B2: No | C2: Bank | D2: Disbursed Date | E2: Start Date | F2: End Date | G2: Principal Amount | H2: Expenses | I2: EMI Amount | J2: Duration (in months) | K2: Total EMI Payment | L2: Total Paid | M2: Repaid | O2: Total Loam Amount
B3: 1 | C3: City | D3: 46048 | E3: 46079 | F3: 46138 | G3: 45000 | H3: =round(373.75+K3-G3,0) -> 1277 | I3: 15301 | J3: 3 | K3: =I3*J3 -> 45903 | L3: =SUM(G3,H3) -> 46277 | M3: Yes | O3: =L7 -> 176008.67
B4: 2 | C4: SCB | D4: 46047 | E4: 46122 | F4: 46275 | G4: 74000 | H4: 3404 | I4: =round(G4/J4, 2) -> 12333.33 | J4: 6 | K4: =I4*J4 -> 73999.98 | L4: =SUM(G4,H4) -> 77404 | M4: No
B5: 3 | C5: EBL | D5: 46082 | E5: 46122 | F5: 46163 | G5: 50000 | H5: =G5*0.0115+(G5-G5/6*J5)*0.023+986 -> 2327.6667 | I5: 8826.14 | J5: 2 | K5: =I5*J5+(G5-G5/6*J5) -> 50985.613 | L5: =G5+H5 -> 52327.667 | M5: Yes
B6: 4 | C6: SCB | D6: 46215 | E6: 46215 | F6: 46305 | G6: 63300 | H6: 0 | I6: 21100 | J6: 3 | K6: 63300 | L6: =G6+H6 -> 63300 | M6: No
B7: Total | G7: =SUM(G3:G6) -> 232300 | H7: =SUM(H3:H6) -> 7008.6667 | I7: =SUM(I3:I6) -> 57560.47 | K7: =SUM(K3:K6) -> 234188.59 | L7: =SUM(L3:L5) -> 176008.67 | M7: No
H10: =L5-I5*2-675 -> 34000.387

Sheet LENT
B2: No | C2: Day | D2: Method | E2: Organizations | F2: Proof ID | G2: Date | H2: Return Date | I2: Amount | K2: Total Lent
B3: 1 | C3: Sunday | D3: NPSB | E3: CITY to SONALI | F3: 101 | G3: 45837 | H3: NOT SURE | I3: 50000 | K3: =I9 -> 190000
B4: 2 | C4: Wednesday | D4: EFTN | E4: CITY to SONALI | F4: 102 | G4: 45910 | H4: NOT SURE | I4: 9000
B5: 3 | C5: Wednesday | D5: EFTN | E5: CITY to SONALI | F5: 103 | G5: 45938 | H5: NOT SURE | I5: 12000
B6: 4 | C6: Monday | D6: EFTN | E6: CITY to SONALI | F6: 104 | G6: 45971 | H6: NOT SURE | I6: 12000
B7: 5 | C7: Tuesday | D7: EFTN | E7: CITY to SONALI | F7: 105 | G7: 46000 | H7: NOT SURE | I7: 12000
B8: 6 | C8: Monday | D8: CASH | E8: HAND to HAND | F8: 106 | G8: 46097 | H8: NOT SURE | I8: 95000
B9: Total | I9: =SUM(I3:I8) -> 190000

Sheet PROOF
B2: ID | C2: Proof
B3: 103
B4: 104
B5: 105

Sheet Current Balance 2025
B2: Type | C2: Availability | D2: Amount | F2: NET AMOUNT | H2: INVESTED | J2: IN HAND
B3: INVESTMENT | C3: LENT OUT | D3: =INVESTMENT!P3 -> 252000 | F3: =D6-LOANS!O3 -> 230991.33 | H3: =INVESTMENT!P3 -> 252000 | J3: =D6-D3-D4 -> 60000
B4: LENT | C4: LENT OUT | D4: 95000
B5: YEARLY SAVINGS | C5: IN HAND | D5: =YEARLY_SAVINGS_2025!H3 -> 60000
B6: Total | D6: =SUM(D3:D5) -> 407000

Sheet YEARLY_SAVINGS_2025
B2: Month | C2: REBATE | D2: SAVINGS | E2: EMERGENCY | F2: Monthly Total | H2: Total Savings
B3: SEP | C3: 15000 | D3: 0 | E3: 0 | F3: =SUM(C3:E3) -> 15000 | H3: =F7 -> 60000
B4: OCT | C4: 15000 | D4: 0 | E4: 0 | F4: =SUM(C4:E4) -> 15000
B5: NOV | C5: 15000 | D5: 0 | E5: 0 | F5: =SUM(C5:E5) -> 15000 | H5: Financial Institution | I5: Savings Type
B6: DEC | C6: 0 | D6: 0 | E6: 0 | F6: 15000 | H6: City Bank | I6: DPS
B7: Yearly Total | C7: =SUM(C3:C6) -> 45000 | D7: =SUM(D3:D6) -> 0 | E7: =SUM(E3:E6) -> 0 | F7: =SUM(F3:F6) -> 60000
